guitk/__init__.py
guitk/__main__.py
guitk/_debug.py
guitk/_on.py
guitk/basewidget.py
guitk/constants.py
guitk/containers.py
guitk/debugwindow.py
guitk/events.py
guitk/frame.py
guitk/image.py
guitk/layout.py
guitk/menu.py
guitk/redirect.py
guitk/scrolledframe.py
guitk/spacer.py
guitk/tk_text.py
guitk/tkroot.py
guitk/tooltips.py
guitk/ttk_button.py
guitk/ttk_checkbutton.py
guitk/ttk_combobox.py
guitk/ttk_entry.py
guitk/ttk_label.py
guitk/ttk_notebook.py
guitk/ttk_panedwindow.py
guitk/ttk_progressbar.py
guitk/ttk_radiobutton.py
guitk/ttk_scale.py
guitk/ttk_separator.py
guitk/ttk_spinbox.py
guitk/ttk_treeview.py
guitk/types.py
guitk/utils.py
guitk/widget.py
guitk/window.py
guitk-0.4.5.dist-info/LICENSE
guitk-0.4.5.dist-info/METADATA
guitk-0.4.5.dist-info/WHEEL
guitk-0.4.5.dist-info/RECORD
