Metadata-Version: 2.1
Name: guitk
Version: 0.4.5
Summary: Python GUI Toolkit for Tk (guitk): simplify the layout and construction of tkinter graphical user interfaces in python.
License: MIT
Author: Rhet Turnbull
Author-email: rturnbull+git@gmail.com
Requires-Python: >=3.9,<4.0
Classifier: License :: OSI Approved :: MIT License
Classifier: Programming Language :: Python :: 3
Classifier: Programming Language :: Python :: 3.9
Classifier: Programming Language :: Python :: 3.10
Classifier: Programming Language :: Python :: 3.11
Classifier: Programming Language :: Python :: 3.12
